cocon_client/__init__.py
cocon_client/_version.py
cocon_client/client.py
cocon_client/errors.py
cocon_client/parser.py
cocon_client/py.typed
cocon_client/types.py
cocon_client-0.2.5.dist-info/METADATA
cocon_client-0.2.5.dist-info/WHEEL
cocon_client-0.2.5.dist-info/licenses/AUTHORS.md
cocon_client-0.2.5.dist-info/licenses/LICENSE
cocon_client-0.2.5.dist-info/licenses/NOTICE.md
cocon_client-0.2.5.dist-info/RECORD
