Metadata-Version: 2.4
Name: cocon_client
Version: 0.2.5
Summary: Async client for Televic CoCon conference API
Project-URL: Homepage, https://github.com/3P-Technologies/cocon_client
Project-URL: Issues, https://github.com/3P-Technologies/cocon_client/issues
Project-URL: Source, https://github.com/3P-Technologies/cocon_client
Project-URL: Commercial License, https://www.trepi.it/en/contacts/
License: Copyright (C) 2025 3P Technologies S.r.l.
License-File: AUTHORS.md
License-File: LICENSE
License-File: NOTICE.md
Classifier: License :: OSI Approved :: GNU Lesser General Public License v3 or later (LGPLv3+)
Classifier: Programming Language :: Python :: 3
Classifier: Programming Language :: Python :: 3 :: Only
Classifier: Programming Language :: Python :: 3.11
Classifier: Programming Language :: Python :: 3.12
Classifier: Programming Language :: Python :: 3.13
Classifier: Typing :: Typed
Requires-Python: >=3.11
Requires-Dist: aiohttp
